{"version": 0.6, "generator": "Overpass API 0.7.56.1004 6cd3eaec", "osm3s": {"timestamp_osm_base": "2020-07-22T01:32:02Z", "copyright": "The data included in this document is from www.openstreetmap.org. The data is made available under ODbL."}, "elements": [{"type": "node", "id": 1748553203, "lat": 41.9301147, "lon": -87.7862591}, {"type": "node", "id": 1748553214, "lat": 41.9301204, "lon": -87.7859536}, {"type": "node", "id": 1748553258, "lat": 41.9301422, "lon": -87.7862581}, {"type": "node", "id": 1748553259, "lat": 41.9301422, "lon": -87.7862658}, {"type": "node", "id": 1748553397, "lat": 41.9301596, "lon": -87.7859438}, {"type": "node", "id": 1748553398, "lat": 41.9301597, "lon": -87.7859533}, {"type": "node", "id": 1748553447, "lat": 41.9301826, "lon": -87.7862648}, {"type": "node", "id": 1748553480, "lat": 41.9301944, "lon": -87.7862646}, {"type": "node", "id": 1748553481, "lat": 41.9301954, "lon": -87.7862599}, {"type": "node", "id": 1748553541, "lat": 41.9302153, "lon": -87.7859462}, {"type": "node", "id": 1748553542, "lat": 41.9302154, "lon": -87.7859543}, {"type": "node", "id": 1748553564, "lat": 41.9302231, "lon": -87.7862394}, {"type": "node", "id": 1748553565, "lat": 41.9302232, "lon": -87.7862604}, {"type": "node", "id": 1748553598, "lat": 41.9302348, "lon": -87.7862371}, {"type": "node", "id": 1748553629, "lat": 41.9302365, "lon": -87.7861331}, {"type": "node", "id": 1748553634, "lat": 41.930238, "lon": -87.7860927}, {"type": "node", "id": 1748553643, "lat": 41.9302395, "lon": -87.7859563}, {"type": "node", "id": 1748553652, "lat": 41.9302424, "lon": -87.7860926}, {"type": "node", "id": 1748553655, "lat": 41.9302426, "lon": -87.786133}, {"type": "node", "id": 5828347295, "lat": 41.9239344, "lon": -87.7923971, "tags": {"addr:city": "Chicago", "addr:housenumber": "6656", "addr:postcode": "60707", "addr:state": "IL", "addr:street": "West Grand Avenue", "amenity": "restaurant", "brand": "Applebee's Neighborhood Grill & Bar", "brand:wikidata": "Q621532", "brand:wikipedia": "en:Applebee's", "cuisine": "american", "name": "Applebee's", "official_name": "Applebee's Neighborhood Grill & Bar"}}, {"type": "node", "id": 6269769547, "lat": 41.9383511, "lon": -87.7938811, "tags": {"addr:city": "Chicago", "addr:housenumber": "6710", "addr:postcode": "60634", "addr:state": "IL", "addr:street": "West Belmont Avenue", "amenity": "bar", "name": "Cafe Prague", "phone": "+1-773-427-7587", "website": "http://www.cafepraguechicago.com"}}, {"type": "node", "id": 6273601317, "lat": 41.9385703, "lon": -87.7798669, "tags": {"addr:city": "Chicago", "addr:housenumber": "6126", "addr:postcode": "60634", "addr:state": "IL", "addr:street": "West Belmont Avenue", "amenity": "cafe", "name": "Cakes & Beyond", "phone": "+1-773-629-4026", "website": "http://www.cakesandbeyondchicago.com/"}}, {"type": "node", "id": 6314869495, "lat": 41.9306732, "lon": -87.801214, "tags": {"addr:city": "Chicago", "addr:housenumber": "7001", "addr:postcode": "60707", "addr:state": "IL", "addr:street": "West Diversey Avenue", "amenity": "bar", "name": "Jacqueline Lounge", "phone": "+1-773-123-4567"}}, {"type": "node", "id": 6324182961, "lat": 41.93836, "lon": -87.7940371, "tags": {"addr:city": "Chicago", "addr:housenumber": "6714", "addr:postcode": "60634", "addr:state": "IL", "addr:street": "West Belmont Avenue", "amenity": "bar", "name": "OverTime Sports Bar and Grill", "phone": "+1-773-993-0533"}}, {"type": "node", "id": 7491974622, "lat": 41.9253711, "lon": -87.7899325, "tags": {"addr:city": "Chicago", "addr:housenumber": "6560", "addr:postcode": "60707", "addr:state": "IL", "addr:street": "West Fullerton Avenue", "amenity": "restaurant", "brand": "Old Country Buffet", "brand:wikidata": "Q75243208", "cuisine": "american", "name": "Old Country Buffet"}}, {"type": "node", "id": 7491974632, "lat": 41.9289613, "lon": -87.7860559, "tags": {"addr:city": "Chicago", "addr:housenumber": "2640", "addr:postcode": "60639", "addr:state": "IL", "addr:street": "North Narragansett Avenue", "addr:unit": "C9-C10", "amenity": "restaurant", "brand": "Buffalo Wild Wings", "brand:wikidata": "Q509255", "brand:wikipedia": "en:Buffalo Wild Wings", "cuisine": "wings", "name": "Buffalo Wild Wings"}}, {"type": "way", "id": 163084241, "nodes": [1748553259, 1748553447, 1748553480, 1748553481, 1748553565, 1748553564, 1748553598, 1748553629, 1748553655, 1748553652, 1748553634, 1748553643, 1748553542, 1748553541, 1748553397, 1748553398, 1748553214, 1748553203, 1748553258, 1748553259], "tags": {"addr:city": "Chicago", "addr:housenumber": "2730", "addr:postcode": "60639", "addr:state": "IL", "addr:street": "North Narragansett Avenue", "addr:street:name": "Narragansett", "addr:street:prefix": "North", "addr:street:type": "Avenue", "amenity": "cafe", "brand": "Starbucks", "brand:wikidata": "Q37158", "brand:wikipedia": "en:Starbucks", "building": "retail", "chicago:building_id": "835110", "cuisine": "coffee_shop", "drive_through": "yes", "name": "Starbucks", "official_name": "Starbucks Coffee", "takeaway": "yes"}}]}