{"version": 0.6, "generator": "Overpass API 0.7.56.3 eb200aeb", "osm3s": {"timestamp_osm_base": "2020-07-04T02:30:03Z", "copyright": "The data included in this document is from www.openstreetmap.org. The data is made available under ODbL."}, "elements": [{"type": "node", "id": 6301778282, "lat": 41.7472739, "lon": -87.5861365, "tags": {"addr:city": "Chicago", "addr:housenumber": "8114", "addr:postcode": "60617", "addr:state": "IL", "addr:street": "South Stony Island Avenue", "amenity": "cafe", "name": "Stony\u2019s Palace Cafe", "phone": "+1-773-978-4535", "website": "https://www.stonyspalace.com/"}}, {"type": "node", "id": 6566849013, "lat": 41.7515441, "lon": -87.5950635, "tags": {"addr:city": "Chicago", "addr:housenumber": "1200", "addr:postcode": "60619", "addr:state": "IL", "addr:street": "East 79th Street", "amenity": "restaurant", "description": "The Woodlawn is a shared kitchen that also has temporary (popup) restaurants. ", "name": "The Woodlawn", "phone": "+1-708-986-3008"}}]}