{"version": 0.6, "generator": "Overpass API 0.7.56.3 eb200aeb", "osm3s": {"timestamp_osm_base": "2020-07-22T19:54:02Z", "copyright": "The data included in this document is from www.openstreetmap.org. The data is made available under ODbL."}, "elements": [{"type": "node", "id": 34877687, "lat": 41.9546467, "lon": -87.7322144}, {"type": "node", "id": 310319075, "lat": 41.9549797, "lon": -87.7328025}, {"type": "node", "id": 1282296222, "lat": 41.9550187, "lon": -87.7328007}, {"type": "node", "id": 1282296365, "lat": 41.9546837, "lon": -87.732215}, {"type": "way", "id": 28256515, "nodes": [310319075, 34877687], "tags": {"bridge": "yes", "electrified": "rail", "frequency": "0", "gauge": "1435", "layer": "1", "name": "O'Hare Branch", "operator": "Chicago Transit Authority", "railway": "subway", "voltage": "600"}}, {"type": "way", "id": 112926175, "nodes": [1282296365, 1282296222], "tags": {"bridge": "yes", "electrified": "rail", "frequency": "0", "gauge": "1435", "name": "O'Hare Branch", "oneway": "yes", "operator": "Chicago Transit Authority", "railway": "subway", "voltage": "600"}}]}